flodym/__init__.py
flodym/_df_to_flodym_array.py
flodym/data_reader.py
flodym/dimensions.py
flodym/example_objects.py
flodym/flodym_array_helper.py
flodym/flodym_arrays.py
flodym/flow_helper.py
flodym/flow_naming.py
flodym/gauss_lobatto.py
flodym/lifetime_models.py
flodym/mfa_definition.py
flodym/mfa_system.py
flodym/processes.py
flodym/stock_helper.py
flodym/stocks.py
flodym/export/__init__.py
flodym/export/array_plotter.py
flodym/export/data_writer.py
flodym/export/helper.py
flodym/export/sankey.py
flodym-0.5.4.dist-info/licenses/LICENSE
flodym-0.5.4.dist-info/METADATA
flodym-0.5.4.dist-info/WHEEL
flodym-0.5.4.dist-info/top_level.txt
flodym-0.5.4.dist-info/RECORD
