Metadata-Version: 2.4
Name: flodym
Version: 0.5.4
Author: Jakob Dürrwächter, Sally Dacie, Merlin Hosak, Bennet Weiss, Leonie Schweiger
Requires-Python: >=3.10
License-File: LICENSE
Requires-Dist: matplotlib>=3.7.1
Requires-Dist: numpy>=1.25.0
Requires-Dist: scipy>=1.11.0
Requires-Dist: PyYAML>=6.0
Requires-Dist: pandas>=2.0.2
Requires-Dist: pickle4>=0.0.1
Requires-Dist: plotly>=5.18.0
Requires-Dist: pydantic>=2.8.2
Requires-Dist: openpyxl>=3.1.5
Requires-Dist: tabulate>=0.9.0
Requires-Dist: deprecated>=1.3.1
Provides-Extra: examples
Requires-Dist: jupyter>=1.1.1; extra == "examples"
Requires-Dist: nbformat>=5.10.4; extra == "examples"
Provides-Extra: tests
Requires-Dist: pytest>=8.3.2; extra == "tests"
Requires-Dist: polyfactory>=2.16.2; extra == "tests"
Provides-Extra: docs
Requires-Dist: sphinx>=7.4.0; extra == "docs"
Requires-Dist: sphinx-pydantic>=0.1.1; extra == "docs"
Requires-Dist: autodoc-pydantic>=2.2.0; extra == "docs"
Requires-Dist: sphinx-rtd-theme>=2.0.0; extra == "docs"
Requires-Dist: myst-parser>=4.0.0; extra == "docs"
Requires-Dist: nbsphinx>=0.9.6; extra == "docs"
Requires-Dist: nbsphinx-link>=1.3.1; extra == "docs"
Requires-Dist: jupyter>=1.1.1; extra == "docs"
Requires-Dist: jupytext>=1.16.4; extra == "docs"
Dynamic: license-file
